h5viewer/__init__.py
h5viewer/main.py
h5viewer-0.7.5.dist-info/LICENCE
h5viewer-0.7.5.dist-info/METADATA
h5viewer-0.7.5.dist-info/WHEEL
h5viewer-0.7.5.dist-info/entry_points.txt
h5viewer-0.7.5.dist-info/top_level.txt
h5viewer-0.7.5.dist-info/RECORD
